Metadata-Version: 2.1
Name: madcat
Version: 7.3
Summary: # MadCat
Home-page: https://github.com/amito-ds/chester
Author: Amit Osi
Author-email: amitosi6666@gmail.com
Requires-Python: >=3.8
Requires-Dist: corextopic (>=1.1)
Requires-Dist: lightgbm (>=3.2.1)
Requires-Dist: matplotlib (>=3.6.3)
Requires-Dist: nltk (>=3.8.1)
Requires-Dist: pandas (>=1.5.2)
Requires-Dist: plotly (>=5.9.0)
Requires-Dist: python-Levenshtein (>=0.20.9)
Requires-Dist: scikit-learn (>=1.2.1)
Requires-Dist: scikit-optimize (>=0.9.0)
Requires-Dist: scipy (>=1.10.0)
Requires-Dist: seaborn (>=0.12.2)
Requires-Dist: textblob (>=0.17.1)
Requires-Dist: tweedie (>=0.0.9)
Requires-Dist: wordcloud (>=1.8.2.2)
Requires-Dist: fuzzywuzzy (>=0.18.0)
